README.md
setup.py
gazerr/__init__.py
gazerr/cli.py
gazerr/estimate.py
gazerr.egg-info/PKG-INFO
gazerr.egg-info/SOURCES.txt
gazerr.egg-info/dependency_links.txt
gazerr.egg-info/entry_points.txt
gazerr.egg-info/requires.txt
gazerr.egg-info/top_level.txt