Metadata-Version: 2.1
Name: gazerr
Version: 0.1.1
Summary: Python library and CLI for estimation of gaze duration error.
Home-page: http://john-hawkins.github.io
Author: John Hawkins
Author-email: john@playgroundxyz.com
License: MIT
Project-URL: Documentation, https://gazerr.readthedocs.io
Project-URL: Source, https://github.com/playground-xyz/gazerr
Project-URL: Tracker, https://github.com/playground-xyz/gazerr/issues
Platform: UNKNOWN
